maptiles/__init__.py
maptiles/maptiles.py
maptiles-0.1.6.dist-info/LICENSE
maptiles-0.1.6.dist-info/METADATA
maptiles-0.1.6.dist-info/WHEEL
maptiles-0.1.6.dist-info/top_level.txt
maptiles-0.1.6.dist-info/RECORD
