Metadata-Version: 2.1
Name: maptiles
Version: 0.1.6
Summary: Create map images and use as plot background
Home-page: https://github.com/kota7/maptiles
Author: Kota Mori
Author-email: kmori05@gmail.com
License: UNKNOWN
Platform: UNKNOWN
License-File: LICENSE
Requires-Dist: matplotlib
Requires-Dist: numpy
Requires-Dist: pillow
Requires-Dist: pyproj
Requires-Dist: requests
